simplemindedshellmcp-0.5.1.dist-info/licenses/LICENSE
src/__init__.py
src/alias_detector.py
src/command_translator.py
src/config_parser.py
src/example_provider.py
src/server.py
src/tool_checker.py
simplemindedshellmcp-0.5.1.dist-info/METADATA
simplemindedshellmcp-0.5.1.dist-info/WHEEL
simplemindedshellmcp-0.5.1.dist-info/entry_points.txt
simplemindedshellmcp-0.5.1.dist-info/top_level.txt
simplemindedshellmcp-0.5.1.dist-info/RECORD
